django_jinja_helpers/__init__.py
django_jinja_helpers/templatetags/__init__.py
django_client_data-0.1.0.dist-info/LICENSE
django_client_data-0.1.0.dist-info/METADATA
django_client_data-0.1.0.dist-info/WHEEL
django_client_data-0.1.0.dist-info/top_level.txt
django_client_data-0.1.0.dist-info/RECORD
