Metadata-Version: 2.1
Name: django-client-data
Version: 0.1.0
Summary: Helpers for using django-jinja
Home-page: https://github.com/enricobarzetti/django_jinja_helpers
Author: Enrico Barzetti
Author-email: enricobarzetti@gmail.com
License: The MIT License
Keywords: django
Platform: OS Independent
Requires-Dist: Django (>=2.0)
